soxai_data/__init__.py
soxai_data/get_ave_data.py
soxai_data/soxai_data.py
soxai_data-0.0.3.dist-info/METADATA
soxai_data-0.0.3.dist-info/WHEEL
soxai_data-0.0.3.dist-info/licenses/LICENSE.txt
soxai_data-0.0.3.dist-info/RECORD
