Metadata-Version: 2.3
Name: soxai_data
Version: 0.0.3
Summary: SOXAI Data Science Library
Project-URL: Homepage, https://soxai.co.jp
Project-URL: Documentation, https://soxai.co.jp/docs
Project-URL: Repository, https://github.com/soxaidev/soxai_data
Project-URL: Bug Tracker, https://github.com/soxaidev/soxai_data/issues
Project-URL: Changelog, https://github.com/soxaidev/soxai_data/blob/master/CHANGELOG.md
Author-email: "SOXAI Inc." <dev@soxai.co.jp>
Maintainer-email: "SOXAI Inc." <dev@soxai.co.jp>
License: MIT License
Keywords: data,science,soxai,soxai-data,soxai_data
Classifier: Development Status :: 4 - Beta
Classifier: Programming Language :: Python
Requires-Python: >=3.8
Requires-Dist: httpx
Requires-Dist: pandas
